mcp_rememberizer_vectordb/__init__.py
mcp_rememberizer_vectordb/server.py
mcp_rememberizer_vectordb/utils.py
mcp_rememberizer_vectordb-0.1.3.dist-info/METADATA
mcp_rememberizer_vectordb-0.1.3.dist-info/WHEEL
mcp_rememberizer_vectordb-0.1.3.dist-info/entry_points.txt
mcp_rememberizer_vectordb-0.1.3.dist-info/licenses/LICENSE
mcp_rememberizer_vectordb-0.1.3.dist-info/RECORD
