Metadata-Version: 2.4
Name: mcp-rememberizer-vectordb
Version: 0.1.3
Summary: A Model Context Protocol server for interacting with Rememberizer Vector Store (https://docs.rememberizer.ai/developer/vector-stores).
Author-email: Rememberizer <support@rememberizer.ai>
License-File: LICENSE
Requires-Python: >=3.11
Requires-Dist: httpx>=0.27.2
Requires-Dist: mcp>=1.0.0
Requires-Dist: python-dotenv>=1.0.1
